nbu/__init__.py
nbu-0.0.0.dist-info/LICENCE.txt
nbu-0.0.0.dist-info/METADATA
nbu-0.0.0.dist-info/WHEEL
nbu-0.0.0.dist-info/top_level.txt
nbu-0.0.0.dist-info/RECORD
